MANIFEST.in
README.rst
setup.cfg
setup.py
bin/gcp_googleanalytics
gcp_googleanalytics/__init__.py
gcp_googleanalytics/account.py
gcp_googleanalytics/blueprint.py
gcp_googleanalytics/columns.py
gcp_googleanalytics/errors.py
gcp_googleanalytics/query.py
gcp_googleanalytics/segments.py
gcp_googleanalytics.egg-info/PKG-INFO
gcp_googleanalytics.egg-info/SOURCES.txt
gcp_googleanalytics.egg-info/dependency_links.txt
gcp_googleanalytics.egg-info/requires.txt
gcp_googleanalytics.egg-info/top_level.txt
gcp_googleanalytics/auth/__init__.py
gcp_googleanalytics/auth/credentials.py
gcp_googleanalytics/auth/keyring.py
gcp_googleanalytics/auth/oauth.py
gcp_googleanalytics/commands/__init__.py
gcp_googleanalytics/commands/authorize.py
gcp_googleanalytics/commands/common.py
gcp_googleanalytics/commands/list.py
gcp_googleanalytics/commands/query.py
gcp_googleanalytics/commands/revoke.py
gcp_googleanalytics/commands/shell.py
gcp_googleanalytics/tests/__init__.py
gcp_googleanalytics/tests/base.py
gcp_googleanalytics/tests/meta.py
gcp_googleanalytics/tests/query.py
gcp_googleanalytics/tests/report.py
gcp_googleanalytics/utils/__init__.py
gcp_googleanalytics/utils/date.py
gcp_googleanalytics/utils/functional.py
gcp_googleanalytics/utils/server.py
gcp_googleanalytics/utils/string.py