Metadata-Version: 1.1
Name: gcp-googleanalytics
Version: 1.0.0
Summary: A wrapper for the Google Analytics API.
Home-page: https://github.com/konchyts-v/gcp-google-analytics/
Author: Stijn Debrouwere
Author-email: stijn@debrouwere.org
License: ISC
Download-URL: https://github.com/konchyts-v/gcp-google-analytics/tarball/master
Keywords: data analytics api wrapper google
Platform: UNKNOWN
Classifier: Development Status :: 4 - Beta
Classifier: Intended Audience :: Developers
Classifier: License :: OSI Approved :: MIT License
Classifier: Operating System :: OS Independent
Classifier: Topic :: Scientific/Engineering :: Information Analysis
Classifier: Programming Language :: Python
Classifier: Programming Language :: Python :: 2
Classifier: Programming Language :: Python :: 2.7
Classifier: Programming Language :: Python :: 3
Classifier: Programming Language :: Python :: 3.4
